[
    {"id":1, "title": "Coversol", "description": "Lona vinílica microperforada de alta resistencia", "image": "https://distribuidoradrops.com.ar/wp-content/uploads/2015/11/coversol_01.jpg", "price": 7500, "unidad": "metro lineal", "categoria": "vinílica", "stock": 200},
    {"id":2, "title": "Nildatex Standard", "description": "Lona vinílica impermeable de alta resistencia con protección UV", "image": "https://http2.mlstatic.com/D_NQ_NP_652064-MLA41477496593_042020-O.webp", "price": 9500, "unidad": "metro lineal", "categoria": "vinílica", "stock": 100},
    {"id":3, "title": "Hulytego", "description": "Lona vinílica impermeable de alta resistencia", "image": "https://static.wixstatic.com/media/a4545a_501fb25873674c6e800e63291b093139.jpg/v1/fill/w_490,h_420,al_c,q_80,enc_auto/a4545a_501fb25873674c6e800e63291b093139.jpg", "price": 8000, "unidad": "metro lineal", "categoria": "vinílica", "stock": 300},
    {"id":4, "title": "Sauleda", "description": "Lona sintética fina premium, repelente al agua, con resitencia UV", "image": "https://lh3.googleusercontent.com/proxy/sIJjf1FST1MG5LRMSimWQ3vBAG5gzQc9rip8vpsqzeWorg8zrNGxjKJDDNjw-joovBxPeH_2zH0j5FEq", "price": 15000, "unidad": "metro lineal", "categoria": "sintética", "stock": 320},
    {"id":5, "title": "Media Sombra Premium", "description": "Media sombra de alto gramaje, tejido cerrado, resistente, 70% de opacidad", "image": "https://http2.mlstatic.com/D_NQ_NP_625388-MLA51652469134_092022-O.webp", "price": 5000, "unidad": "metro lineal", "categoria": "mediasombra", "stock": 150},
    {"id":6, "title": "Zonda 900", "description": "Lona vinílica de alta resistencia antidesgarre", "image": "https://http2.mlstatic.com/D_NQ_NP_664327-MLA31036780881_062019-O.webp", "price": 8500, "unidad": "metro lineal", "categoria": "vinílica", "stock": 220},
    {"id":7, "title": "Zonda 1100", "description": "Lona vinílica de alta resistencia antidesgarre con protección UV", "image": "https://sanisidrolonasar.vtexassets.com/arquivos/ids/158641/cobertura-de-camion-el-zonda-900-fucsia-01.jpg?v=637648917908230000", "price": 9500, "unidad": "metro lineal", "categoria": "vinílica", "stock": 60},
    {"id":8, "title": "Algodón 8", "description": "Lona de algodón natural alta densidad 15grcm2", "image": "https://sanisidrolonasar.vtexassets.com/arquivos/ids/162171-800-auto?v=637920278779330000&width=800&height=auto&aspect=true", "price": 9500, "unidad": "metro lineal", "categoria": "algodón", "stock": 100}
]